armanc/__init__.py
armanc/django/inertia/__init__.py
armanc/django/inertia/apps.py
armanc/django/inertia/models.py
armanc/django/inertia/response.py
armanc/django/inertia/views.py
armanc/django/inertia/adapters/__init__.py
armanc/django/inertia/adapters/forms.py
armanc/django/inertia/adapters/registry.py
armanc/django/inertia/adapters/test_forms.py
armanc/django/inertia/templates/inertia.html
armanc/django/inertia/templates/inertia_ssr.html
armanc_toolkit-0.1.2.dist-info/METADATA
armanc_toolkit-0.1.2.dist-info/WHEEL
armanc_toolkit-0.1.2.dist-info/top_level.txt
armanc_toolkit-0.1.2.dist-info/RECORD
