Metadata-Version: 2.4
Name: armanc-toolkit
Version: 0.1.2
Summary: A comprehensive toolkit containing various utilities for Django and Python development
Author-email: Armanc <29763280+armancdev@users.noreply.github.com>
License-Expression: MIT
Project-URL: Homepage, https://github.com/armancdev/armancs-django
Project-URL: Bug Reports, https://github.com/armancdev/armancs-django/issues
Project-URL: Source, https://github.com/armancdev/armancs-django
Keywords: django,inertia,toolkit,web-development
Classifier: Development Status :: 4 - Beta
Classifier: Intended Audience :: Developers
Classifier: Operating System :: OS Independent
Classifier: Programming Language :: Python :: 3
Classifier: Programming Language :: Python :: 3.13
Classifier: Framework :: Django
Classifier: Framework :: Django :: 4.2
Classifier: Framework :: Django :: 5.0
Classifier: Topic :: Software Development :: Libraries :: Python Modules
Classifier: Topic :: Internet :: WWW/HTTP :: Dynamic Content
Requires-Python: >=3.13
Requires-Dist: django<6.0,>=4.2
Requires-Dist: djantic2>=1.0.5
Requires-Dist: inertia-django>=1.2.0
Requires-Dist: pydantic>=2.11.7
Requires-Dist: telepath>=0.3.1
